[{"inputs":[{"internalType":"address","name":"chips","type":"address"}],"stateMutability":"nonpayable","type":"constructor"},{"anonymous":false,"inputs":[{"indexed":true,"internalType":"address","name":"user","type":"address"},{"indexed":false,"internalType":"uint48","name":"amount","type":"uint48"},{"indexed":false,"internalType":"uint48","name":"timestamp","type":"uint48"}],"name":"ChipsGiven","type":"event"},{"anonymous":false,"inputs":[{"indexed":true,"internalType":"address","name":"user","type":"address"},{"indexed":false,"internalType":"uint48","name":"amount","type":"uint48"},{"indexed":false,"internalType":"uint48","name":"timestamp","type":"uint48"}],"name":"ChipsTaken","type":"event"},{"anonymous":false,"inputs":[{"indexed":true,"internalType":"address","name":"player","type":"address"},{"indexed":false,"internalType":"uint48","name":"timestamp","type":"uint48"},{"indexed":false,"internalType":"uint48","name":"initialChipCount","type":"uint48"}],"name":"NewMember","type":"event"},{"inputs":[{"internalType":"address","name":"game","type":"address"}],"name":"addGame","outputs":[],"stateMutability":"nonpayable","type":"function"},{"inputs":[],"name":"chipContract","outputs":[{"internalType":"contract ChipInterface","name":"","type":"address"}],"stateMutability":"view","type":"function"},{"inputs":[{"internalType":"address","name":"to","type":"address"},{"internalType":"uint48","name":"amount","type":"uint48"}],"name":"giveChips","outputs":[],"stateMutability":"nonpayable","type":"function"},{"inputs":[],"name":"initialChipCount","outputs":[{"internalType":"uint48","name":"","type":"uint48"}],"stateMutability":"view","type":"function"},{"inputs":[{"internalType":"address","name":"_address","type":"address"}],"name":"isGame","outputs":[{"internalType":"bool","name":"","type":"bool"}],"stateMutability":"view","type":"function"},{"inputs":[{"internalType":"address","name":"_address","type":"address"}],"name":"isMember","outputs":[{"internalType":"bool","name":"","type":"bool"}],"stateMutability":"view","type":"function"},{"inputs":[],"name":"joinCasino","outputs":[],"stateMutability":"payable","type":"function"},{"inputs":[{"internalType":"address","name":"","type":"address"}],"name":"members","outputs":[{"internalType":"bool","name":"","type":"bool"}],"stateMutability":"view","type":"function"},{"inputs":[],"name":"membershipFee","outputs":[{"internalType":"uint256","name":"","type":"uint256"}],"stateMutability":"view","type":"function"},{"inputs":[{"internalType":"address","name":"game","type":"address"}],"name":"removeGame","outputs":[],"stateMutability":"nonpayable","type":"function"},{"inputs":[{"internalType":"address","name":"newContract","type":"address"},{"internalType":"bool","name":"supplyMembers","type":"bool"}],"name":"setChipContract","outputs":[],"stateMutability":"nonpayable","type":"function"},{"inputs":[{"internalType":"uint48","name":"newChipCount","type":"uint48"}],"name":"setInitialChipCount","outputs":[],"stateMutability":"nonpayable","type":"function"},{"inputs":[{"internalType":"uint256","name":"fee","type":"uint256"}],"name":"setMembershipFee","outputs":[],"stateMutability":"nonpayable","type":"function"},{"inputs":[{"internalType":"address","name":"from","type":"address"},{"internalType":"uint48","name":"amount","type":"uint48"}],"name":"takeChips","outputs":[],"stateMutability":"nonpayable","type":"function"},{"inputs":[{"internalType":"address payable","name":"newOwner","type":"address"}],"name":"transferOwnership","outputs":[],"stateMutability":"nonpayable","type":"function"}]